Workbook

Sheet CHASE #3444
A1: CHASE #3444
A2: MONTH | B2: BEGIN BALANCE | C2: CASH / CHECK DEPOSIT | D2: NO1 SUSHI 88 CORKBBO ACH | E2: VEOLIA WATER | F2: ORANGE & ROCKLAND | G2: WITHDRAWAL BRANCH 0964 | H2: AMAZON | I2: BILL PAY:VEOLIA WATER NEW Y 200045 6BU1T6KR | J2: BILL PAY:ORANGE & ROCKLAND 136130 6BQ1P6KR | K2: INTERNET TRF TO CLIENT-ADDED TRANSFER ACCOUNT | L2: WITHDRAWAL BRANCH 0964 NEW YORK | M2: POS MAC AMAZON.COM*NX6 SEATTLE WA | N2: POS MAC AMAZON.COM*9O5 SEATTLE WA | O2: POS MAC AMAZON.COM*SB8 SEATTLE WA | P2: NYS DTF PIT TAX PAYMNT | Q2: TOTAL CREDIT | R2: DEBIT | S2: ENDING BALANCE
A3: 45383 | B3: 0 | Q3: =SUM(C3:P3) | S3: =B3+Q3-R3
A4: 45413 | B4: =S3 | Q4: =SUM(C4:P4) | S4: =B4+Q4-R4
A5: 45444 | B5: =S4 | Q5: =SUM(C5:P5) | S5: =B5+Q5-R5
A6: 45474 | B6: =S5 | Q6: =SUM(C6:P6) | S6: =B6+Q6-R6
A7: 45505 | B7: =S6 | Q7: =SUM(C7:P7) | S7: =B7+Q7-R7
A8: 45536 | B8: =S7 | Q8: =SUM(C8:P8) | S8: =B8+Q8-R8
A9: 45566 | B9: =S8 | Q9: =SUM(C9:P9) | S9: =B9+Q9-R9
A10: 45597 | B10: =S9 | Q10: =SUM(C10:P10) | S10: =B10+Q10-R10
A11: 45627 | B11: =S10 | Q11: =SUM(C11:P11) | S11: =B11+Q11-R11
A12: 45658 | B12: =S11 | Q12: =SUM(C12:P12) | S12: =B12+Q12-R12
A13: 45689 | B13: =S12 | Q13: =SUM(C13:P13) | S13: =B13+Q13-R13
A14: 45717 | B14: =S13 | Q14: =SUM(C14:P14) | S14: =B14+Q14-R14
A15: TOTAL | C15: =SUM(C3:C14) | D15: =SUM(D3:D14) | E15: =SUM(E3:E14) | F15: =SUM(F3:F14) | G15: =SUM(G3:G14) | H15: =SUM(H3:H14) | I15: =SUM(I3:I14) | J15: =SUM(J3:J14) | ... R15: =SUM(R3:R14) | S15: =S14

Sheet CHASE DETIAL#3444
A1: Merchant | B1: ='CHASE #3444'!A3 | C1: ='CHASE #3444'!A4 | D1: ='CHASE #3444'!A5 | E1: ='CHASE #3444'!A6 | F1: ='CHASE #3444'!A7 | G1: ='CHASE #3444'!A8 | H1: ='CHASE #3444'!A9 | I1: ='CHASE #3444'!A10 | J1: ='CHASE #3444'!A11 | K1: ='CHASE #3444'!A12 | L1: ='CHASE #3444'!A13 | M1: ='CHASE #3444'!A14 | N1: Total | O1: Category
A2: 434 / Nys Commission | N2: =SUM(B2,C2,D2,E2,F2,G2,H2,I2,J2,K2,L2,M2) | O2: GERCORY
A3: Amazon Prime*Zh8618Uz3 Amzn.Com/Bill WA | N3: =SUM(B3,C3,D3,E3,F3,G3,H3,I3,J3,K3,L3,M3) | O3: GERCORY
A4: Amazon.Com*N22Fjseattlewa US | N4: =SUM(B4,C4,D4,E4,F4,G4,H4,I4,J4,K4,L4,M4) | O4: GERCORY
A5: Amazon.Comseattlewa US | N5: =SUM(B5,C5,D5,E5,F5,G5,H5,I5,J5,K5,L5,M5) | O5: GERCORY
A6: Amex Epayment ACH Pmt | N6: =SUM(B6,C6,D6,E6,F6,G6,H6,I6,J6,K6,L6,M6) | O6: GERCORY
A7: Arrow Bank Na Web Pmt | N7: =SUM(B7,C7,D7,E7,F7,G7,H7,I7,J7,K7,L7,M7) | O7: GERCORY
A8: Bill Pay:Associated Mutual 210061 Ubq1P6Kr | N8: =SUM(B8,C8,D8,E8,F8,G8,H8,I8,J8,K8,L8,M8) | O8: GERCORY
A9: Bill Pay:New York State Ins 237224 4Bq1P6Kr | N9: =SUM(B9,C9,D9,E9,F9,G9,H9,I9,J9,K9,L9,M9) | O9: OFFICE EXPENSE
A10: Bill Pay:Orange & Rockland 136130 6Bq1P6Kr | N10: =SUM(B10,C10,D10,E10,F10,G10,H10,I10,J10,K10,L10,M10) | O10: OFFICE EXPENSE
A11: Bill Pay:Orange & Rockland 879293 5Bq1P6Kr | N11: =SUM(B11,C11,D11,E11,F11,G11,H11,I11,J11,K11,L11,M11) | O11: OFFICE EXPENSE
A12: Bill Pay:Veolia Water New Y 200045 6Bu1T6Kr | N12: =SUM(B12,C12,D12,E12,F12,G12,H12,I12,J12,K12,L12,M12) | O12: OFFICE EXPENSE
A13: Bill Pay:Veolia Water New Y 200054 Hbu1T6Kr | N13: =SUM(B13,C13,D13,E13,F13,G13,H13,I13,J13,K13,L13,M13) | O13: OFFICE EXPENSE
... A40: Withdrawal Branch 0964 New York | N40: =SUM(B40,C40,D40,E40,F40,G40,H40,I40,J40,K40,L40,M40) | O40: SUPPLY
A41: discover Bank Net/Mobile | N41: =SUM(B41,C41,D41,E41,F41,G41,H41,I41,J41,K41,L41,M41)
A42: Total | B42: =SUM(B2:B41) | C42: =SUM(C2:C41) | D42: =SUM(D2:D41) | E42: =SUM(E2:E41) | F42: =SUM(F2:F41) | G42: =SUM(G2:G41) | H42: =SUM(H2:H41) | I42: =SUM(I2:I41) | ... M42: =SUM(M2:M41) | N42: =SUM(B42,C42,D42,E42,F42,G42,H42,I42,J42,K42,L42,M42)

Sheet CHASE CC#5235
A1: Merchant | B1: 45748 | C1: 45778 | D1: 45809 | E1: 45839 | F1: 45870 | G1: 45901 | H1: 45931 | I1: 45962 | J1: 45992 | K1: 46023 | L1: 46054 | M1: 46082 | N1: 46113 | O1: Total | P1: Category | Q1: 46240
A2: 434 / Nys Commission | O2: =SUM(B2,C2,D2,E2,F2,G2,H2,I2,J2,K2,L2,M2,N2,Q2) | P2: GERCORY
A3: Amazon Prime*Zh8618Uz3 Amzn.Com/Bill WA | O3: =SUM(B3,C3,D3,E3,F3,G3,H3,I3,J3,K3,L3,M3,N3,Q3) | P3: GERCORY
A4: Amazon.Com*N22Fjseattlewa US | O4: =SUM(B4,C4,D4,E4,F4,G4,H4,I4,J4,K4,L4,M4,N4,Q4) | P4: GERCORY
A5: Amazon.Comseattlewa US | O5: =SUM(B5,C5,D5,E5,F5,G5,H5,I5,J5,K5,L5,M5,N5,Q5) | P5: GERCORY
A6: Amex Epayment ACH Pmt | O6: =SUM(B6,C6,D6,E6,F6,G6,H6,I6,J6,K6,L6,M6,N6,Q6) | P6: GERCORY
A7: Arrow Bank Na Web Pmt | O7: =SUM(B7,C7,D7,E7,F7,G7,H7,I7,J7,K7,L7,M7,N7,Q7) | P7: GERCORY
A8: Bill Pay:Associated Mutual 210061 Ubq1P6Kr | O8: =SUM(B8,C8,D8,E8,F8,G8,H8,I8,J8,K8,L8,M8,N8,Q8) | P8: GERCORY
A9: Bill Pay:New York State Ins 237224 4Bq1P6Kr | O9: =SUM(B9,C9,D9,E9,F9,G9,H9,I9,J9,K9,L9,M9,N9,Q9) | P9: OFFICE EXPENSE
A10: Bill Pay:Orange & Rockland 136130 6Bq1P6Kr | O10: =SUM(B10,C10,D10,E10,F10,G10,H10,I10,J10,K10,L10,M10,N10,Q10) | P10: OFFICE EXPENSE
A11: Bill Pay:Orange & Rockland 879293 5Bq1P6Kr | O11: =SUM(B11,C11,D11,E11,F11,G11,H11,I11,J11,K11,L11,M11,N11,Q11) | P11: OFFICE EXPENSE
A12: Bill Pay:Veolia Water New Y 200045 6Bu1T6Kr | O12: =SUM(B12,C12,D12,E12,F12,G12,H12,I12,J12,K12,L12,M12,N12,Q12) | P12: OFFICE EXPENSE
A13: Bill Pay:Veolia Water New Y 200054 Hbu1T6Kr | O13: =SUM(B13,C13,D13,E13,F13,G13,H13,I13,J13,K13,L13,M13,N13,Q13) | P13: OFFICE EXPENSE
... A40: Withdrawal Branch 0964 New York | O40: =SUM(B40,C40,D40,E40,F40,G40,H40,I40,J40,K40,L40,M40,N40,Q40) | P40: SUPPLY
A41: Total | B41: =SUM(B2:B40) | C41: =SUM(C2:C40) | D41: =SUM(D2:D40) | E41: =SUM(E2:E40) | F41: =SUM(F2:F40) | G41: =SUM(G2:G40) | H41: =SUM(H2:H40) | I41: =SUM(I2:I40) | ... N41: =SUM(N2:N40) | O41: =SUM(B41,C41,D41,E41,F41,G41,H41,I41,J41,K41,L41,M41,N41,Q41) | Q41: =SUM(Q2:Q40)
A43: BEGIN | B43: =0 | C43: =B46 | D43: =C46 | E43: =D46 | F43: =E46 | G43: =F46 | H43: =G46 | I43: =H46 | J43: =I46 | ... N43: =M46
A44: ADD | B44: =B41 | C44: =C41 | D44: =D41 | E44: =E41 | F44: =F41 | G44: =G41 | H44: =H41 | I44: =I41 | ... N44: =N41
A45: LESS
A46: ENDING` | B46: =B43+B44-B45 | C46: =C43+C44-C45 | D46: =D43+D44-D45 | E46: =E43+E44-E45 | F46: =F43+F44-F45 | G46: =G43+G44-G45 | H46: =H43+H44-H45 | I46: =I43+I44-I45 | ... N46: =N43+N44-N45

Sheet Sheet3
